{
    "Blocks": [
        {
            "Box": {
                "LLx": 0,
                "LLy": 0,
                "Physical Layer": "null",
                "URx": 144480,
                "URy": 73920
            },
            "Height": 73920,
            "Name": "X0",
            "Pins": [
                {
                    "Internal Metal": [
                        {
                            "LLx": 14340,
                            "LLy": 39160,
                            "Physical Layer": "M3",
                            "URx": 14900,
                            "URy": 52400
                        },
                        {
                            "LLx": 129580,
                            "LLy": 39160,
                            "Physical Layer": "M3",
                            "URx": 130140,
                            "URy": 52400
                        },
                        {
                            "LLx": 14340,
                            "LLy": 44990,
                            "Physical Layer": "M3",
                            "URx": 14900,
                            "URy": 45730
                        },
                        {
                            "LLx": 14620,
                            "LLy": 45080,
                            "Physical Layer": "M2",
                            "URx": 129860,
                            "URy": 45640
                        },
                        {
                            "LLx": 129580,
                            "LLy": 44990,
                            "Physical Layer": "M3",
                            "URx": 130140,
                            "URy": 45730
                        }
                    ],
                    "Name": "CLK0"
                },
                {
                    "Internal Metal": [
                        {
                            "LLx": 57340,
                            "LLy": 21520,
                            "Physical Layer": "M3",
                            "URx": 57900,
                            "URy": 34760
                        },
                        {
                            "LLx": 86580,
                            "LLy": 21520,
                            "Physical Layer": "M3",
                            "URx": 87140,
                            "URy": 34760
                        },
                        {
                            "LLx": 57340,
                            "LLy": 27350,
                            "Physical Layer": "M3",
                            "URx": 57900,
                            "URy": 28090
                        },
                        {
                            "LLx": 57620,
                            "LLy": 27440,
                            "Physical Layer": "M2",
                            "URx": 86860,
                            "URy": 28000
                        },
                        {
                            "LLx": 86580,
                            "LLy": 27350,
                            "Physical Layer": "M3",
                            "URx": 87140,
                            "URy": 28090
                        }
                    ],
                    "Name": "CLK0B"
                },
                {
                    "Internal Metal": [
                        {
                            "LLx": 57340,
                            "LLy": 39160,
                            "Physical Layer": "M3",
                            "URx": 57900,
                            "URy": 52400
                        },
                        {
                            "LLx": 86580,
                            "LLy": 39160,
                            "Physical Layer": "M3",
                            "URx": 87140,
                            "URy": 52400
                        },
                        {
                            "LLx": 57340,
                            "LLy": 44990,
                            "Physical Layer": "M3",
                            "URx": 57900,
                            "URy": 45730
                        },
                        {
                            "LLx": 57620,
                            "LLy": 44560,
                            "Physical Layer": "M4",
                            "URx": 86860,
                            "URy": 46160
                        },
                        {
                            "LLx": 86580,
                            "LLy": 44990,
                            "Physical Layer": "M3",
                            "URx": 87140,
                            "URy": 45730
                        }
                    ],
                    "Name": "CLK1"
                },
                {
                    "Internal Metal": [
                        {
                            "LLx": 14340,
                            "LLy": 21520,
                            "Physical Layer": "M3",
                            "URx": 14900,
                            "URy": 34760
                        },
                        {
                            "LLx": 129580,
                            "LLy": 21520,
                            "Physical Layer": "M3",
                            "URx": 130140,
                            "URy": 34760
                        },
                        {
                            "LLx": 14340,
                            "LLy": 27350,
                            "Physical Layer": "M3",
                            "URx": 14900,
                            "URy": 28090
                        },
                        {
                            "LLx": 14620,
                            "LLy": 26920,
                            "Physical Layer": "M4",
                            "URx": 129860,
                            "URy": 28520
                        },
                        {
                            "LLx": 129580,
                            "LLy": 27350,
                            "Physical Layer": "M3",
                            "URx": 130140,
                            "URy": 28090
                        }
                    ],
                    "Name": "CLK1B"
                },
                {
                    "Internal Metal": [
                        {
                            "LLx": 34920,
                            "LLy": 70280,
                            "Physical Layer": "M2",
                            "URx": 37320,
                            "URy": 70840
                        },
                        {
                            "LLx": 34920,
                            "LLy": 51800,
                            "Physical Layer": "M2",
                            "URx": 37320,
                            "URy": 52360
                        },
                        {
                            "LLx": 34940,
                            "LLy": 70280,
                            "Physical Layer": "M2",
                            "URx": 35580,
                            "URy": 70840
                        },
                        {
                            "LLx": 34980,
                            "LLy": 52080,
                            "Physical Layer": "M3",
                            "URx": 35540,
                            "URy": 70560
                        },
                        {
                            "LLx": 34940,
                            "LLy": 51800,
                            "Physical Layer": "M2",
                            "URx": 35580,
                            "URy": 52360
                        },
                        {
                            "LLx": 107160,
                            "LLy": 70280,
                            "Physical Layer": "M2",
                            "URx": 109560,
                            "URy": 70840
                        },
                        {
                            "LLx": 107160,
                            "LLy": 51800,
                            "Physical Layer": "M2",
                            "URx": 109560,
                            "URy": 52360
                        },
                        {
                            "LLx": 108900,
                            "LLy": 70280,
                            "Physical Layer": "M2",
                            "URx": 109540,
                            "URy": 70840
                        },
                        {
                            "LLx": 108940,
                            "LLy": 52080,
                            "Physical Layer": "M3",
                            "URx": 109500,
                            "URy": 70560
                        },
                        {
                            "LLx": 108900,
                            "LLy": 51800,
                            "Physical Layer": "M2",
                            "URx": 109540,
                            "URy": 52360
                        },
                        {
                            "LLx": 36980,
                            "LLy": 70280,
                            "Physical Layer": "M2",
                            "URx": 107500,
                            "URy": 70840
                        }
                    ],
                    "Name": "VGND"
                },
                {
                    "Internal Metal": [
                        {
                            "LLx": 34060,
                            "LLy": 14000,
                            "Physical Layer": "M2",
                            "URx": 38180,
                            "URy": 14560
                        },
                        {
                            "LLx": 34060,
                            "LLy": 32480,
                            "Physical Layer": "M2",
                            "URx": 38180,
                            "URy": 33040
                        },
                        {
                            "LLx": 34080,
                            "LLy": 14000,
                            "Physical Layer": "M2",
                            "URx": 34720,
                            "URy": 14560
                        },
                        {
                            "LLx": 34120,
                            "LLy": 14280,
                            "Physical Layer": "M3",
                            "URx": 34680,
                            "URy": 32760
                        },
                        {
                            "LLx": 34080,
                            "LLy": 32480,
                            "Physical Layer": "M2",
                            "URx": 34720,
                            "URy": 33040
                        }
                    ],
                    "Name": "VHIGH"
                },
                {
                    "Internal Metal": [
                        {
                            "LLx": 106300,
                            "LLy": 59360,
                            "Physical Layer": "M2",
                            "URx": 110420,
                            "URy": 59920
                        },
                        {
                            "LLx": 106300,
                            "LLy": 40880,
                            "Physical Layer": "M2",
                            "URx": 110420,
                            "URy": 41440
                        },
                        {
                            "LLx": 109760,
                            "LLy": 59360,
                            "Physical Layer": "M2",
                            "URx": 110400,
                            "URy": 59920
                        },
                        {
                            "LLx": 109800,
                            "LLy": 41160,
                            "Physical Layer": "M3",
                            "URx": 110360,
                            "URy": 59640
                        },
                        {
                            "LLx": 109760,
                            "LLy": 40880,
                            "Physical Layer": "M2",
                            "URx": 110400,
                            "URy": 41440
                        }
                    ],
                    "Name": "VLOW"
                },
                {
                    "Internal Metal": [
                        {
                            "LLx": 34060,
                            "LLy": 59360,
                            "Physical Layer": "M2",
                            "URx": 38180,
                            "URy": 59920
                        },
                        {
                            "LLx": 34060,
                            "LLy": 40880,
                            "Physical Layer": "M2",
                            "URx": 38180,
                            "URy": 41440
                        },
                        {
                            "LLx": 34080,
                            "LLy": 59360,
                            "Physical Layer": "M2",
                            "URx": 34720,
                            "URy": 59920
                        },
                        {
                            "LLx": 34120,
                            "LLy": 41160,
                            "Physical Layer": "M3",
                            "URx": 34680,
                            "URy": 59640
                        },
                        {
                            "LLx": 34080,
                            "LLy": 40880,
                            "Physical Layer": "M2",
                            "URx": 34720,
                            "URy": 41440
                        },
                        {
                            "LLx": 106300,
                            "LLy": 14000,
                            "Physical Layer": "M2",
                            "URx": 110420,
                            "URy": 14560
                        },
                        {
                            "LLx": 106300,
                            "LLy": 32480,
                            "Physical Layer": "M2",
                            "URx": 110420,
                            "URy": 33040
                        },
                        {
                            "LLx": 109760,
                            "LLy": 14000,
                            "Physical Layer": "M2",
                            "URx": 110400,
                            "URy": 14560
                        },
                        {
                            "LLx": 109800,
                            "LLy": 14280,
                            "Physical Layer": "M3",
                            "URx": 110360,
                            "URy": 32760
                        },
                        {
                            "LLx": 109760,
                            "LLy": 32480,
                            "Physical Layer": "M2",
                            "URx": 110400,
                            "URy": 33040
                        },
                        {
                            "LLx": 37840,
                            "LLy": 40880,
                            "Physical Layer": "M2",
                            "URx": 39560,
                            "URy": 41440
                        },
                        {
                            "LLx": 39310,
                            "LLy": 32760,
                            "Physical Layer": "M1",
                            "URx": 39810,
                            "URy": 41160
                        },
                        {
                            "LLx": 39560,
                            "LLy": 32480,
                            "Physical Layer": "M2",
                            "URx": 106640,
                            "URy": 33040
                        }
                    ],
                    "Name": "VMID"
                },
                {
                    "Internal Metal": [
                        {
                            "LLx": 34920,
                            "LLy": 3080,
                            "Physical Layer": "M2",
                            "URx": 37320,
                            "URy": 3640
                        },
                        {
                            "LLx": 34920,
                            "LLy": 21560,
                            "Physical Layer": "M2",
                            "URx": 37320,
                            "URy": 22120
                        },
                        {
                            "LLx": 34940,
                            "LLy": 3080,
                            "Physical Layer": "M2",
                            "URx": 35580,
                            "URy": 3640
                        },
                        {
                            "LLx": 34980,
                            "LLy": 3360,
                            "Physical Layer": "M3",
                            "URx": 35540,
                            "URy": 21840
                        },
                        {
                            "LLx": 34940,
                            "LLy": 21560,
                            "Physical Layer": "M2",
                            "URx": 35580,
                            "URy": 22120
                        },
                        {
                            "LLx": 107160,
                            "LLy": 3080,
                            "Physical Layer": "M2",
                            "URx": 109560,
                            "URy": 3640
                        },
                        {
                            "LLx": 107160,
                            "LLy": 21560,
                            "Physical Layer": "M2",
                            "URx": 109560,
                            "URy": 22120
                        },
                        {
                            "LLx": 108900,
                            "LLy": 3080,
                            "Physical Layer": "M2",
                            "URx": 109540,
                            "URy": 3640
                        },
                        {
                            "LLx": 108940,
                            "LLy": 3360,
                            "Physical Layer": "M3",
                            "URx": 109500,
                            "URy": 21840
                        },
                        {
                            "LLx": 108900,
                            "LLy": 21560,
                            "Physical Layer": "M2",
                            "URx": 109540,
                            "URy": 22120
                        },
                        {
                            "LLx": 36980,
                            "LLy": 3080,
                            "Physical Layer": "M2",
                            "URx": 107500,
                            "URy": 3640
                        }
                    ],
                    "Name": "VPWR"
                },
                {
                    "Internal Metal": [
                        {
                            "LLx": 105440,
                            "LLy": 34160,
                            "Physical Layer": "M2",
                            "URx": 107840,
                            "URy": 34720
                        },
                        {
                            "LLx": 105440,
                            "LLy": 39200,
                            "Physical Layer": "M2",
                            "URx": 107840,
                            "URy": 39760
                        },
                        {
                            "LLx": 106320,
                            "LLy": 34160,
                            "Physical Layer": "M2",
                            "URx": 106960,
                            "URy": 34720
                        },
                        {
                            "LLx": 106360,
                            "LLy": 34440,
                            "Physical Layer": "M3",
                            "URx": 106920,
                            "URy": 39480
                        },
                        {
                            "LLx": 106320,
                            "LLy": 39200,
                            "Physical Layer": "M2",
                            "URx": 106960,
                            "URy": 39760
                        }
                    ],
                    "Name": "Y0_BOT"
                },
                {
                    "Internal Metal": [
                        {
                            "LLx": 36640,
                            "LLy": 34160,
                            "Physical Layer": "M2",
                            "URx": 39040,
                            "URy": 34720
                        },
                        {
                            "LLx": 36640,
                            "LLy": 39200,
                            "Physical Layer": "M2",
                            "URx": 39040,
                            "URy": 39760
                        },
                        {
                            "LLx": 37520,
                            "LLy": 34160,
                            "Physical Layer": "M2",
                            "URx": 38160,
                            "URy": 34720
                        },
                        {
                            "LLx": 37560,
                            "LLy": 34440,
                            "Physical Layer": "M3",
                            "URx": 38120,
                            "URy": 39480
                        },
                        {
                            "LLx": 37520,
                            "LLy": 39200,
                            "Physical Layer": "M2",
                            "URx": 38160,
                            "URy": 39760
                        }
                    ],
                    "Name": "Y0_TOP"
                },
                {
                    "Internal Metal": [
                        {
                            "LLx": 107160,
                            "LLy": 33320,
                            "Physical Layer": "M2",
                            "URx": 109560,
                            "URy": 33880
                        },
                        {
                            "LLx": 107160,
                            "LLy": 40040,
                            "Physical Layer": "M2",
                            "URx": 109560,
                            "URy": 40600
                        },
                        {
                            "LLx": 108040,
                            "LLy": 33320,
                            "Physical Layer": "M2",
                            "URx": 108680,
                            "URy": 33880
                        },
                        {
                            "LLx": 108080,
                            "LLy": 33600,
                            "Physical Layer": "M3",
                            "URx": 108640,
                            "URy": 40320
                        },
                        {
                            "LLx": 108040,
                            "LLy": 40040,
                            "Physical Layer": "M2",
                            "URx": 108680,
                            "URy": 40600
                        }
                    ],
                    "Name": "Y1_BOT"
                },
                {
                    "Internal Metal": [
                        {
                            "LLx": 34920,
                            "LLy": 33320,
                            "Physical Layer": "M2",
                            "URx": 37320,
                            "URy": 33880
                        },
                        {
                            "LLx": 34920,
                            "LLy": 40040,
                            "Physical Layer": "M2",
                            "URx": 37320,
                            "URy": 40600
                        },
                        {
                            "LLx": 35800,
                            "LLy": 33320,
                            "Physical Layer": "M2",
                            "URx": 36440,
                            "URy": 33880
                        },
                        {
                            "LLx": 35840,
                            "LLy": 33600,
                            "Physical Layer": "M3",
                            "URx": 36400,
                            "URy": 40320
                        },
                        {
                            "LLx": 35800,
                            "LLy": 40040,
                            "Physical Layer": "M2",
                            "URx": 36440,
                            "URy": 40600
                        }
                    ],
                    "Name": "Y1_TOP"
                }
            ],
            "Width": 144480
        }
    ],
    "Cell Name": "DCDC_CONV2TO1",
    "Cell box": {
        "LLx": 0,
        "LLy": 0,
        "Physical Layer": "null",
        "URx": 144480,
        "URy": 73920
    },
    "Gcell": [
        {
            "Physical Layer": 0,
            "x": 43000,
            "y": 36960
        },
        {
            "Physical Layer": 0,
            "x": 115240,
            "y": 36960
        },
        {
            "Physical Layer": 1,
            "x": 43000,
            "y": 36960
        },
        {
            "Physical Layer": 1,
            "x": 115240,
            "y": 36960
        },
        {
            "Physical Layer": 2,
            "x": 43000,
            "y": 36960
        },
        {
            "Physical Layer": 2,
            "x": 115240,
            "y": 36960
        },
        {
            "Physical Layer": 3,
            "x": 43000,
            "y": 36960
        },
        {
            "Physical Layer": 3,
            "x": 115240,
            "y": 36960
        },
        {
            "Physical Layer": 4,
            "x": 43000,
            "y": 36960
        },
        {
            "Physical Layer": 4,
            "x": 115240,
            "y": 36960
        }
    ],
    "Glbaol_Routes": [
        {
            "global_path": [
                {
                    "Physical Layer ll": 2,
                    "Physical Layer ur": 2,
                    "llx": 43000,
                    "lly": 36960,
                    "urx": 43000,
                    "ury": 36960
                }
            ],
            "name": "CLK0",
            "terminals": [
                {
                    "Physical Layer": 2,
                    "x": 43000,
                    "y": 36960
                },
                {
                    "Physical Layer": 2,
                    "x": 115240,
                    "y": 36960
                }
            ]
        },
        {
            "global_path": [
                {
                    "Physical Layer ll": 2,
                    "Physical Layer ur": 2,
                    "llx": 43000,
                    "lly": 36960,
                    "urx": 43000,
                    "ury": 36960
                }
            ],
            "name": "CLK0B",
            "terminals": [
                {
                    "Physical Layer": 2,
                    "x": 43000,
                    "y": 36960
                },
                {
                    "Physical Layer": 2,
                    "x": 115240,
                    "y": 36960
                }
            ]
        },
        {
            "global_path": [
                {
                    "Physical Layer ll": 2,
                    "Physical Layer ur": 2,
                    "llx": 43000,
                    "lly": 36960,
                    "urx": 43000,
                    "ury": 36960
                }
            ],
            "name": "CLK1",
            "terminals": [
                {
                    "Physical Layer": 2,
                    "x": 43000,
                    "y": 36960
                },
                {
                    "Physical Layer": 2,
                    "x": 115240,
                    "y": 36960
                }
            ]
        },
        {
            "global_path": [
                {
                    "Physical Layer ll": 2,
                    "Physical Layer ur": 2,
                    "llx": 43000,
                    "lly": 36960,
                    "urx": 43000,
                    "ury": 36960
                }
            ],
            "name": "CLK1B",
            "terminals": [
                {
                    "Physical Layer": 2,
                    "x": 43000,
                    "y": 36960
                },
                {
                    "Physical Layer": 2,
                    "x": 115240,
                    "y": 36960
                }
            ]
        },
        {
            "global_path": [
                {
                    "Physical Layer ll": 1,
                    "Physical Layer ur": 1,
                    "llx": 43000,
                    "lly": 36960,
                    "urx": 43000,
                    "ury": 36960
                }
            ],
            "name": "VGND",
            "terminals": [
                {
                    "Physical Layer": 1,
                    "x": 43000,
                    "y": 36960
                },
                {
                    "Physical Layer": 1,
                    "x": 115240,
                    "y": 36960
                },
                {
                    "Physical Layer": 2,
                    "x": 43000,
                    "y": 36960
                },
                {
                    "Physical Layer": 2,
                    "x": 115240,
                    "y": 36960
                }
            ]
        },
        {
            "global_path": [
                {
                    "Physical Layer ll": 1,
                    "Physical Layer ur": 1,
                    "llx": 43000,
                    "lly": 36960,
                    "urx": 43000,
                    "ury": 36960
                }
            ],
            "name": "VHIGH",
            "terminals": [
                {
                    "Physical Layer": 1,
                    "x": 43000,
                    "y": 36960
                },
                {
                    "Physical Layer": 2,
                    "x": 43000,
                    "y": 36960
                }
            ]
        },
        {
            "global_path": [
                {
                    "Physical Layer ll": 1,
                    "Physical Layer ur": 1,
                    "llx": 115240,
                    "lly": 36960,
                    "urx": 115240,
                    "ury": 36960
                }
            ],
            "name": "VLOW",
            "terminals": [
                {
                    "Physical Layer": 1,
                    "x": 115240,
                    "y": 36960
                },
                {
                    "Physical Layer": 2,
                    "x": 115240,
                    "y": 36960
                }
            ]
        },
        {
            "global_path": [
                {
                    "Physical Layer ll": 0,
                    "Physical Layer ur": 0,
                    "llx": 43000,
                    "lly": 36960,
                    "urx": 43000,
                    "ury": 36960
                }
            ],
            "name": "VMID",
            "terminals": [
                {
                    "Physical Layer": 0,
                    "x": 43000,
                    "y": 36960
                },
                {
                    "Physical Layer": 1,
                    "x": 43000,
                    "y": 36960
                },
                {
                    "Physical Layer": 1,
                    "x": 115240,
                    "y": 36960
                },
                {
                    "Physical Layer": 2,
                    "x": 43000,
                    "y": 36960
                },
                {
                    "Physical Layer": 2,
                    "x": 115240,
                    "y": 36960
                }
            ]
        },
        {
            "global_path": [
                {
                    "Physical Layer ll": 1,
                    "Physical Layer ur": 1,
                    "llx": 43000,
                    "lly": 36960,
                    "urx": 43000,
                    "ury": 36960
                }
            ],
            "name": "VPWR",
            "terminals": [
                {
                    "Physical Layer": 1,
                    "x": 43000,
                    "y": 36960
                },
                {
                    "Physical Layer": 1,
                    "x": 115240,
                    "y": 36960
                },
                {
                    "Physical Layer": 2,
                    "x": 43000,
                    "y": 36960
                },
                {
                    "Physical Layer": 2,
                    "x": 115240,
                    "y": 36960
                }
            ]
        },
        {
            "global_path": [
                {
                    "Physical Layer ll": 1,
                    "Physical Layer ur": 1,
                    "llx": 115240,
                    "lly": 36960,
                    "urx": 115240,
                    "ury": 36960
                }
            ],
            "name": "Y0_BOT",
            "terminals": [
                {
                    "Physical Layer": 1,
                    "x": 115240,
                    "y": 36960
                },
                {
                    "Physical Layer": 2,
                    "x": 115240,
                    "y": 36960
                }
            ]
        },
        {
            "global_path": [
                {
                    "Physical Layer ll": 1,
                    "Physical Layer ur": 1,
                    "llx": 43000,
                    "lly": 36960,
                    "urx": 43000,
                    "ury": 36960
                }
            ],
            "name": "Y0_TOP",
            "terminals": [
                {
                    "Physical Layer": 1,
                    "x": 43000,
                    "y": 36960
                },
                {
                    "Physical Layer": 2,
                    "x": 43000,
                    "y": 36960
                }
            ]
        },
        {
            "global_path": [
                {
                    "Physical Layer ll": 1,
                    "Physical Layer ur": 1,
                    "llx": 115240,
                    "lly": 36960,
                    "urx": 115240,
                    "ury": 36960
                }
            ],
            "name": "Y1_BOT",
            "terminals": [
                {
                    "Physical Layer": 1,
                    "x": 115240,
                    "y": 36960
                },
                {
                    "Physical Layer": 2,
                    "x": 115240,
                    "y": 36960
                }
            ]
        },
        {
            "global_path": [
                {
                    "Physical Layer ll": 1,
                    "Physical Layer ur": 1,
                    "llx": 43000,
                    "lly": 36960,
                    "urx": 43000,
                    "ury": 36960
                }
            ],
            "name": "Y1_TOP",
            "terminals": [
                {
                    "Physical Layer": 1,
                    "x": 43000,
                    "y": 36960
                },
                {
                    "Physical Layer": 2,
                    "x": 43000,
                    "y": 36960
                }
            ]
        }
    ],
    "Istop": true,
    "Units": "0.5nm"
}